{"version":3,"kind":"Article","sha256":"320906a401c5e17e8161cb0aa8f872f71cc0d57ddcdea1e4ee6ff0ed2519fe87","slug":"index","location":"/README.md","dependencies":[],"frontmatter":{"title":"MPAS-Viewer Cookbook","content_includes_title":false,"authors":[{"nameParsed":{"literal":"The visualization of MPAS data","given":"The","non_dropping_particle":"visualization of","family":"MPAS data"},"name":"The visualization of MPAS data","id":"contributors-myst-generated-uid-0"}],"open_access":true,"license":{"content":{"id":"CC-BY-4.0","url":"https://creativecommons.org/licenses/by/4.0/","name":"Creative Commons Attribution 4.0 International","free":true,"CC":true},"code":{"id":"Apache-2.0","url":"https://opensource.org/licenses/Apache-2.0","name":"Apache License 2.0","free":true,"osi":true}},"github":"https://github.com/projectpythia/mpasviewer-cookbook","copyright":"2026","affiliations":[{"id":"UAlbany","name":"University at Albany (SUNY)","department":"Atmospheric and Environmental Sciences","url":"https://www.albany.edu/daes"},{"id":"CISL","name":"NSF National Center for Atmospheric Research","department":"Computational and Information Systems Lab","url":"https://www.cisl.ucar.edu"},{"id":"Unidata","name":"NSF Unidata","url":"https://www.unidata.ucar.edu"},{"id":"Argonne","name":"Argonne National Laboratory","department":"Environmental Science Division","url":"https://www.anl.gov/evs"},{"id":"CarbonPlan","name":"CarbonPlan","url":"https://carbonplan.org"},{"id":"NVIDIA","name":"NVIDIA Corporation","url":"https://www.nvidia.com/"}],"source_url":"https://github.com/projectpythia/mpasviewer-cookbook/blob/main/README.md","edit_url":"https://github.com/projectpythia/mpasviewer-cookbook/edit/main/README.md","thumbnail":"/mpasviewer-cookbook/build/mpas_01-48f8bee66ef55470b3cf7c6bfe2b87a0.png","exports":[{"format":"md","filename":"README.md","url":"/mpasviewer-cookbook/build/README-5809362d8812a2ca35f57638cb8f26d0.md"}]},"mdast":{"type":"root","children":[{"type":"block","children":[{"type":"table","children":[{"type":"tableRow","children":[{"type":"tableCell","children":[{"type":"image","url":"/mpasviewer-cookbook/build/mpas_01-48f8bee66ef55470b3cf7c6bfe2b87a0.png","width":200,"key":"Gibz4IxTBB","urlSource":"thumbnails/mpas_01.png"}],"key":"JzLRcOrgLC"},{"type":"tableCell","children":[{"type":"image","url":"/mpasviewer-cookbook/build/thumbnail-5a2a02850a12d4b4b6f9ddacb49b6f30.png","width":200,"key":"U4p7ZmblKD","urlSource":"thumbnails/thumbnail.png"}],"key":"y6vafH78Ty"}],"key":"KdUVnPtHI1"}],"key":"PfBWRw09cF"},{"type":"paragraph","position":{"start":{"line":11,"column":1},"end":{"line":13,"column":1}},"children":[{"type":"link","url":"https://github.com/ProjectPythia/cookbook-template/actions/workflows/nightly-build.yaml","position":{"start":{"line":11,"column":1},"end":{"line":11,"column":1}},"children":[{"type":"image","url":"/mpasviewer-cookbook/build/06605fa84b8680f0497b7822b6283a3e.svg","alt":"nightly-build","position":{"start":{"line":11,"column":1},"end":{"line":11,"column":1}},"key":"i5OX5kWvnA","urlSource":"https://github.com/ProjectPythia/cookbook-template/actions/workflows/nightly-build.yaml/badge.svg"}],"urlSource":"https://github.com/ProjectPythia/cookbook-template/actions/workflows/nightly-build.yaml","error":true,"key":"f363gMtPrh"},{"type":"text","value":"\n","position":{"start":{"line":11,"column":1},"end":{"line":11,"column":1}},"key":"wCfAJmQo1Y"},{"type":"link","url":"https://binder.projectpythia.org/v2/gh/ProjectPythia/cookbook-template/main?labpath=notebooks","position":{"start":{"line":11,"column":1},"end":{"line":11,"column":1}},"children":[{"type":"image","url":"/mpasviewer-cookbook/build/31e3f387ea168934ca949c27e9927ea4.svg","alt":"Binder","position":{"start":{"line":11,"column":1},"end":{"line":11,"column":1}},"key":"IkD1RwRTbl","urlSource":"https://binder.projectpythia.org/badge_logo.svg"}],"urlSource":"https://binder.projectpythia.org/v2/gh/ProjectPythia/cookbook-template/main?labpath=notebooks","key":"U7HNmSJcOI"},{"type":"text","value":"\n","position":{"start":{"line":11,"column":1},"end":{"line":11,"column":1}},"key":"lp5vfk5G4M"},{"type":"cite","url":"https://doi.org/10.5281/zenodo.20753191","position":{"start":{"line":11,"column":1},"end":{"line":11,"column":1}},"children":[{"type":"image","url":"/mpasviewer-cookbook/build/72a08caa5cbe5f9cce5999dbd1a81dfd.svg","alt":"DOI","position":{"start":{"line":11,"column":1},"end":{"line":11,"column":1}},"key":"OjXboMbBqd","urlSource":"https://zenodo.org/badge/475509405.svg"}],"kind":"narrative","label":"https://doi.org/10.5281/zenodo.20753191","identifier":"https://doi.org/10.5281/zenodo.20753191","enumerator":"1","key":"vfSq6wNTlA"}],"key":"hxZ000gK5E"},{"type":"paragraph","position":{"start":{"line":17,"column":1},"end":{"line":17,"column":1}},"children":[{"type":"text","value":"This ","position":{"start":{"line":17,"column":1},"end":{"line":17,"column":1}},"key":"yY92g9KfiH"},{"type":"strong","position":{"start":{"line":17,"column":1},"end":{"line":17,"column":1}},"children":[{"type":"text","value":"“Pythia Cookbook”","position":{"start":{"line":17,"column":1},"end":{"line":17,"column":1}},"key":"Q3XbEkSvoa"}],"key":"y4MUhCXPKg"},{"type":"text","value":" was started during the ","position":{"start":{"line":17,"column":1},"end":{"line":17,"column":1}},"key":"Qo8dEXf0e1"},{"type":"strong","position":{"start":{"line":17,"column":1},"end":{"line":17,"column":1}},"children":[{"type":"text","value":"Project Pythia June 15-18 2026 in Boulder, CO at the NCAR Mesa Lab","position":{"start":{"line":17,"column":1},"end":{"line":17,"column":1}},"key":"A3UQ3KCPN2"}],"key":"HTizZBWQeT"},{"type":"text","value":".","position":{"start":{"line":17,"column":1},"end":{"line":17,"column":1}},"key":"G0wLRWAEnJ"}],"key":"CxxFNpkH2m"},{"type":"paragraph","position":{"start":{"line":19,"column":1},"end":{"line":19,"column":1}},"children":[{"type":"text","value":"This ","position":{"start":{"line":19,"column":1},"end":{"line":19,"column":1}},"key":"eXsM98kroR"},{"type":"strong","position":{"start":{"line":19,"column":1},"end":{"line":19,"column":1}},"children":[{"type":"text","value":"MPAS-Viewer Cookbook","position":{"start":{"line":19,"column":1},"end":{"line":19,"column":1}},"key":"VxvAcvzBEj"}],"key":"vR4e2CLW6g"},{"type":"text","value":" aims to provide a comprehensive guide for utilizing MPAS-Viewer, a lightweight and efficient Python-based visualization tool designed specifically for MPAS data. Unlike common approaches that rely on triangulation or iterative polygon construction, MPAS-Viewer operates directly on the native mesh, treating each model cell as the fundamental plotting unit. This approach avoids computationally expensive preprocessing steps and significantly reduces rendering time.","position":{"start":{"line":19,"column":1},"end":{"line":19,"column":1}},"key":"cpVxMHSxBG"}],"key":"skztgZAr4B"},{"type":"heading","depth":2,"position":{"start":{"line":21,"column":1},"end":{"line":21,"column":1}},"children":[{"type":"text","value":"Motivation","position":{"start":{"line":21,"column":1},"end":{"line":21,"column":1}},"key":"KfyRm2WFgF"}],"identifier":"motivation","label":"Motivation","html_id":"motivation","implicit":true,"key":"qJgHAS1Hmd"},{"type":"paragraph","position":{"start":{"line":23,"column":1},"end":{"line":23,"column":1}},"children":[{"type":"text","value":"The development of this Pythia cookbook is motivated by the need to make MPAS-Viewer accessible, reproducible, and easy to adopt within the scientific community. By combining clear explanations with practical, executable examples, this cookbook provides users with a guided pathway to rapidly visualize, explore, and analyze MPAS-A outputs. It emphasizes simplicity, performance, and interactivity, enabling workflows that support animations, time exploration, and efficient data interrogation.","position":{"start":{"line":23,"column":1},"end":{"line":23,"column":1}},"key":"byFozwsIqC"}],"key":"n68oHFEjHA"},{"type":"heading","depth":2,"position":{"start":{"line":25,"column":1},"end":{"line":25,"column":1}},"children":[{"type":"text","value":"Authors","position":{"start":{"line":25,"column":1},"end":{"line":25,"column":1}},"key":"UJSyOzd6VI"}],"identifier":"authors","label":"Authors","html_id":"authors","implicit":true,"key":"axCU2F8qmu"},{"type":"table","position":{"start":{"line":27,"column":1},"end":{"line":33,"column":1}},"children":[{"type":"tableRow","position":{"start":{"line":27,"column":1},"end":{"line":27,"column":1}},"children":[{"type":"tableCell","header":true,"position":{"start":{"line":27,"column":1},"end":{"line":27,"column":1}},"children":[{"type":"text","value":"Name","position":{"start":{"line":27,"column":1},"end":{"line":27,"column":1}},"key":"TwqeDK2hR9"}],"key":"qfcOsJHlcw"},{"type":"tableCell","header":true,"position":{"start":{"line":27,"column":1},"end":{"line":27,"column":1}},"children":[{"type":"text","value":"Affiliation","position":{"start":{"line":27,"column":1},"end":{"line":27,"column":1}},"key":"l4GghDqBoM"}],"key":"iyNShLiDpf"}],"key":"YgWie2ETK5"},{"type":"tableRow","position":{"start":{"line":29,"column":1},"end":{"line":29,"column":1}},"children":[{"type":"tableCell","position":{"start":{"line":29,"column":1},"end":{"line":29,"column":1}},"children":[{"type":"link","url":"https://github.com/jhbravo","position":{"start":{"line":29,"column":1},"end":{"line":29,"column":1}},"children":[{"type":"text","value":"Jorge Bravo","position":{"start":{"line":29,"column":1},"end":{"line":29,"column":1}},"key":"ndRwR0t6Mw"}],"urlSource":"https://github.com/jhbravo","error":true,"key":"D47XWL2ve3"}],"key":"R7KRIjZ7T4"},{"type":"tableCell","position":{"start":{"line":29,"column":1},"end":{"line":29,"column":1}},"children":[{"type":"text","value":"Stevens Institute of Technology","position":{"start":{"line":29,"column":1},"end":{"line":29,"column":1}},"key":"K4Mhaur6n5"}],"key":"lHNGIuEeDZ"}],"key":"x5lSfhPUfq"},{"type":"tableRow","position":{"start":{"line":30,"column":1},"end":{"line":30,"column":1}},"children":[{"type":"tableCell","position":{"start":{"line":30,"column":1},"end":{"line":30,"column":1}},"children":[{"type":"link","url":"https://github.com/melissazavaleta","position":{"start":{"line":30,"column":1},"end":{"line":30,"column":1}},"children":[{"type":"text","value":"Melissa Zavaleta","position":{"start":{"line":30,"column":1},"end":{"line":30,"column":1}},"key":"qU2A7UEkT2"}],"urlSource":"https://github.com/melissazavaleta","error":true,"key":"axDQUO8YqJ"}],"key":"NBKfGSJVFj"},{"type":"tableCell","position":{"start":{"line":30,"column":1},"end":{"line":30,"column":1}},"children":[{"type":"text","value":"Florida Institute of Technology","position":{"start":{"line":30,"column":1},"end":{"line":30,"column":1}},"key":"QcTs0zdHgr"}],"key":"ih9ipUZTkw"}],"key":"u4Z3CEMori"},{"type":"tableRow","position":{"start":{"line":31,"column":1},"end":{"line":31,"column":1}},"children":[{"type":"tableCell","position":{"start":{"line":31,"column":1},"end":{"line":31,"column":1}},"children":[{"type":"link","url":"https://github.com/bmcondo","position":{"start":{"line":31,"column":1},"end":{"line":31,"column":1}},"children":[{"type":"text","value":"Bella Condo","position":{"start":{"line":31,"column":1},"end":{"line":31,"column":1}},"key":"QG0wnXhdgD"}],"urlSource":"https://github.com/bmcondo","error":true,"key":"ZTRrA676RJ"}],"key":"J4UsEiJTpc"},{"type":"tableCell","position":{"start":{"line":31,"column":1},"end":{"line":31,"column":1}},"children":[{"type":"text","value":"Texas A&M University","position":{"start":{"line":31,"column":1},"end":{"line":31,"column":1}},"key":"uF2ttuSUCW"}],"key":"jrhtKGwROC"}],"key":"ps1phhypCK"},{"type":"tableRow","position":{"start":{"line":32,"column":1},"end":{"line":32,"column":1}},"children":[{"type":"tableCell","position":{"start":{"line":32,"column":1},"end":{"line":32,"column":1}},"children":[{"type":"link","url":"https://github.com/ming80302","position":{"start":{"line":32,"column":1},"end":{"line":32,"column":1}},"children":[{"type":"text","value":"Ge Ming","position":{"start":{"line":32,"column":1},"end":{"line":32,"column":1}},"key":"ulbDcyAjza"}],"urlSource":"https://github.com/ming80302","error":true,"key":"eqnRMtJ61Z"}],"key":"jt30De909b"},{"type":"tableCell","position":{"start":{"line":32,"column":1},"end":{"line":32,"column":1}},"children":[{"type":"text","value":"MMM/NCAR","position":{"start":{"line":32,"column":1},"end":{"line":32,"column":1}},"key":"omD9nQEeAx"}],"key":"NYUfxHL7sh"}],"key":"M8ryLbijkU"},{"type":"tableRow","position":{"start":{"line":33,"column":1},"end":{"line":33,"column":1}},"children":[{"type":"tableCell","position":{"start":{"line":33,"column":1},"end":{"line":33,"column":1}},"children":[{"type":"link","url":"https://github.com/nathanagarwal314","position":{"start":{"line":33,"column":1},"end":{"line":33,"column":1}},"children":[{"type":"text","value":"Agarwal Nathan","position":{"start":{"line":33,"column":1},"end":{"line":33,"column":1}},"key":"uKaT4t6flR"}],"urlSource":"https://github.com/nathanagarwal314","error":true,"key":"cJ5yVl8GLi"}],"key":"aBBXQq0bbC"},{"type":"tableCell","position":{"start":{"line":33,"column":1},"end":{"line":33,"column":1}},"children":[{"type":"text","value":"Johns Hopkins University","position":{"start":{"line":33,"column":1},"end":{"line":33,"column":1}},"key":"pO5JU0Rtsx"}],"key":"Qqx0CPxrRf"}],"key":"QWobjOmYVB"}],"key":"xdcBRdhJxk"},{"type":"heading","depth":3,"position":{"start":{"line":35,"column":1},"end":{"line":35,"column":1}},"children":[{"type":"text","value":"Contributors","position":{"start":{"line":35,"column":1},"end":{"line":35,"column":1}},"key":"h6rRlcFtFe"}],"identifier":"contributors","label":"Contributors","html_id":"contributors","implicit":true,"key":"gkE2pciFW6"},{"type":"link","url":"https://github.com/ProjectPythia/mpasviewer-cookbook/graphs/contributors","children":[{"type":"image","url":"/mpasviewer-cookbook/build/71ba35e43a79d3c84c9de3253d6c1939.svg","key":"rdL3ysHUWa","urlSource":"https://contrib.rocks/image?repo=ProjectPythia/mpasviewer-cookbook"}],"urlSource":"https://github.com/ProjectPythia/mpasviewer-cookbook/graphs/contributors","error":true,"key":"PxnRIyL7ka"},{"type":"heading","depth":2,"position":{"start":{"line":41,"column":1},"end":{"line":41,"column":1}},"children":[{"type":"text","value":"Structure","position":{"start":{"line":41,"column":1},"end":{"line":41,"column":1}},"key":"DhWlYMcoeU"}],"identifier":"structure","label":"Structure","html_id":"structure","implicit":true,"key":"XXBjoO39aL"},{"type":"paragraph","position":{"start":{"line":43,"column":1},"end":{"line":43,"column":1}},"children":[{"type":"text","value":"This practical development manual serves as an example of how to collect, manage, and present various MPAS-A data.","position":{"start":{"line":43,"column":1},"end":{"line":43,"column":1}},"key":"Wotm079E0K"}],"key":"KTRidVOBgb"},{"type":"heading","depth":3,"position":{"start":{"line":45,"column":1},"end":{"line":45,"column":1}},"children":[{"type":"text","value":"Foundations","position":{"start":{"line":45,"column":1},"end":{"line":45,"column":1}},"key":"t4t1s005RG"}],"identifier":"foundations","label":"Foundations","html_id":"foundations","implicit":true,"key":"OHZiM4EPVc"},{"type":"paragraph","position":{"start":{"line":47,"column":1},"end":{"line":47,"column":1}},"children":[{"type":"text","value":"The ","position":{"start":{"line":47,"column":1},"end":{"line":47,"column":1}},"key":"aEzDexrUiR"},{"type":"strong","position":{"start":{"line":47,"column":1},"end":{"line":47,"column":1}},"children":[{"type":"text","value":"Model for Prediction Across Scales Atmosphere (MPAS-A)","position":{"start":{"line":47,"column":1},"end":{"line":47,"column":1}},"key":"qFJPSoY7jt"}],"key":"ZVeCjJpzZH"},{"type":"text","value":" is an advanced atmospheric model designed to represent weather systems across both regional and global scales. Its defining feature is the use of an unstructured, variable-resolution mesh, often described as a honeycomb-like grid, which allows high resolution in regions of interest while maintaining coarser resolution elsewhere. This design enables MPAS-A to efficiently capture fine-scale phenomena such as convection and storms without sacrificing the ability to simulate large-scale atmospheric dynamics.","position":{"start":{"line":47,"column":1},"end":{"line":47,"column":1}},"key":"bgotwaE7VE"}],"key":"o7muQV88vH"},{"type":"paragraph","position":{"start":{"line":49,"column":1},"end":{"line":49,"column":1}},"children":[{"type":"text","value":"Despite these advantages, the unstructured nature of the MPAS mesh introduces challenges for data visualization and analysis. Although MPAS-A outputs are stored in NetCDF format, they cannot be treated like conventional gridded raster data. Proper handling of the data requires knowledge of the mesh connectivity, including vertices, edges, and cell centroids, which complicates otherwise straightforward visualization tasks. As a result, rapid inspection and exploratory analysis of MPAS-A outputs can become time-consuming and technically demanding.","position":{"start":{"line":49,"column":1},"end":{"line":49,"column":1}},"key":"jeqtdoLIaP"}],"key":"uKViJgr6CL"},{"type":"heading","depth":3,"position":{"start":{"line":51,"column":1},"end":{"line":51,"column":1}},"children":[{"type":"text","value":"Example workflows","position":{"start":{"line":51,"column":1},"end":{"line":51,"column":1}},"key":"cazhgiLkiD"}],"identifier":"example-workflows","label":"Example workflows","html_id":"example-workflows","implicit":true,"key":"UDd5Eguvsb"},{"type":"paragraph","position":{"start":{"line":53,"column":1},"end":{"line":53,"column":1}},"children":[{"type":"text","value":"Several notebooks with the following structure can be found in the notebooks directory:","position":{"start":{"line":53,"column":1},"end":{"line":53,"column":1}},"key":"UGOyUcxjuG"}],"key":"iEeqDViUf6"},{"type":"heading","depth":2,"position":{"start":{"line":55,"column":1},"end":{"line":55,"column":1}},"children":[{"type":"text","value":"Running the Notebooks","position":{"start":{"line":55,"column":1},"end":{"line":55,"column":1}},"key":"JmeFKdWFsP"}],"identifier":"running-the-notebooks","label":"Running the Notebooks","html_id":"running-the-notebooks","implicit":true,"key":"ZdliTwSdJl"},{"type":"paragraph","position":{"start":{"line":57,"column":1},"end":{"line":57,"column":1}},"children":[{"type":"text","value":"You can either run the notebooks in the Cookbook using ","position":{"start":{"line":57,"column":1},"end":{"line":57,"column":1}},"key":"MtVzkkeLBT"},{"type":"link","url":"https://binder.projectpythia.org/","position":{"start":{"line":57,"column":1},"end":{"line":57,"column":1}},"children":[{"type":"text","value":"Binder","position":{"start":{"line":57,"column":1},"end":{"line":57,"column":1}},"key":"pxKYsLNXWC"}],"urlSource":"https://binder.projectpythia.org/","key":"vBqvoS62f0"},{"type":"text","value":" or on your local machine.","position":{"start":{"line":57,"column":1},"end":{"line":57,"column":1}},"key":"FIdJeeTyqS"}],"key":"Y6Xg0DIagj"},{"type":"heading","depth":3,"position":{"start":{"line":59,"column":1},"end":{"line":59,"column":1}},"children":[{"type":"text","value":"Running on Binder","position":{"start":{"line":59,"column":1},"end":{"line":59,"column":1}},"key":"xYaE84zhQt"}],"identifier":"running-on-binder","label":"Running on Binder","html_id":"running-on-binder","implicit":true,"key":"eZUZmDKm7k"},{"type":"paragraph","position":{"start":{"line":61,"column":1},"end":{"line":74,"column":1}},"children":[{"type":"text","value":"The simplest way to interact with a Jupyter Notebook is through\n","position":{"start":{"line":61,"column":1},"end":{"line":61,"column":1}},"key":"jX9BBor76U"},{"type":"link","url":"https://binder.projectpythia.org/","position":{"start":{"line":61,"column":1},"end":{"line":61,"column":1}},"children":[{"type":"text","value":"Binder","position":{"start":{"line":61,"column":1},"end":{"line":61,"column":1}},"key":"GRlrF5mhUb"}],"urlSource":"https://binder.projectpythia.org/","key":"JsT1yPi752"},{"type":"text","value":", which enables “one click”\nexecution in the cloud. Simply navigate your mouse to\nthe top right corner of the book chapter you are viewing and click\non the rocket ship icon (see screenshots ","position":{"start":{"line":61,"column":1},"end":{"line":61,"column":1}},"key":"mxs5izKxir"},{"type":"link","url":"https://foundations.projectpythia.org/preamble/how-to-use/#running-pythia-foundations-examples","position":{"start":{"line":61,"column":1},"end":{"line":61,"column":1}},"children":[{"type":"text","value":"here","position":{"start":{"line":61,"column":1},"end":{"line":61,"column":1}},"key":"vl9Ip3EKvx"}],"urlSource":"https://foundations.projectpythia.org/preamble/how-to-use/#running-pythia-foundations-examples","key":"QBlkKM9bws"},{"type":"text","value":"),\nand a text box will appear. Type or paste the Pythia Binder link\n(","position":{"start":{"line":61,"column":1},"end":{"line":61,"column":1}},"key":"k9YOXWcAFa"},{"type":"inlineCode","value":"https://binder.projectpythia.org","position":{"start":{"line":61,"column":1},"end":{"line":61,"column":1}},"key":"F2vsVn5c3f"},{"type":"text","value":") and click “Launch”.\nAfter a few moments you should be presented with a\nnotebook that you can interact with. You’ll be able to execute code\nand even change the example programs. At first the code cells\nhave no output, until you execute them by pressing\n","position":{"start":{"line":61,"column":1},"end":{"line":61,"column":1}},"key":"xX3DBF6KWf"},{"type":"keyboard","children":[{"type":"text","value":"Shift","key":"VL4U3ocT79"}],"key":"mFZIhLaP5Y"},{"type":"text","value":"+","position":{"start":{"line":61,"column":1},"end":{"line":61,"column":1}},"key":"vk2kyYzVhU"},{"type":"keyboard","children":[{"type":"text","value":"Enter","key":"C5pNkdMsVi"}],"key":"wHGk7f0chk"},{"type":"text","value":". Complete details on how to interact with\na live Jupyter notebook are described in the Pythia Foundations chapter ","position":{"start":{"line":61,"column":1},"end":{"line":61,"column":1}},"key":"pRqkPUfFXy"},{"type":"link","url":"https://foundations.projectpythia.org/foundations/getting-started-jupyter","position":{"start":{"line":61,"column":1},"end":{"line":61,"column":1}},"children":[{"type":"text","value":"Getting Started with\nJupyter","position":{"start":{"line":61,"column":1},"end":{"line":61,"column":1}},"key":"LYild3oi7K"}],"urlSource":"https://foundations.projectpythia.org/foundations/getting-started-jupyter","key":"bS49slW4qA"},{"type":"text","value":".","position":{"start":{"line":61,"column":1},"end":{"line":61,"column":1}},"key":"U8WlVmW21h"}],"key":"IIpov1WaaZ"},{"type":"paragraph","position":{"start":{"line":76,"column":1},"end":{"line":78,"column":1}},"children":[{"type":"text","value":"Note, not all Cookbook chapters are executable. If you do not see\nthe rocket ship icon, such as on this page, you are not viewing an\nexecutable book chapter.","position":{"start":{"line":76,"column":1},"end":{"line":76,"column":1}},"key":"Lh8v4wdSnc"}],"key":"Nm0IVLarn7"},{"type":"heading","depth":3,"position":{"start":{"line":81,"column":1},"end":{"line":81,"column":1}},"children":[{"type":"text","value":"Running on Your Own Machine","position":{"start":{"line":81,"column":1},"end":{"line":81,"column":1}},"key":"y2zXeCD52k"}],"identifier":"running-on-your-own-machine","label":"Running on Your Own Machine","html_id":"running-on-your-own-machine","implicit":true,"key":"uC9j4lPstF"},{"type":"paragraph","position":{"start":{"line":83,"column":1},"end":{"line":83,"column":1}},"children":[{"type":"text","value":"If you are interested in running this material locally on your computer, you will need to follow this workflow:","position":{"start":{"line":83,"column":1},"end":{"line":83,"column":1}},"key":"gqd13eo3ta"}],"key":"ztlzmxCArY"},{"type":"paragraph","position":{"start":{"line":85,"column":1},"end":{"line":85,"column":1}},"children":[{"type":"text","value":"(Replace “mpasviewer-cookbook” with the title of your cookbooks)","position":{"start":{"line":85,"column":1},"end":{"line":85,"column":1}},"key":"PokNtdJUcX"}],"key":"LwO6p6oqmQ"},{"type":"list","ordered":true,"start":1,"spread":false,"position":{"start":{"line":87,"column":1},"end":{"line":106,"column":1}},"children":[{"type":"listItem","spread":true,"position":{"start":{"line":87,"column":1},"end":{"line":92,"column":1}},"children":[{"type":"paragraph","position":{"start":{"line":87,"column":1},"end":{"line":87,"column":1}},"children":[{"type":"text","value":"Clone the ","position":{"start":{"line":87,"column":1},"end":{"line":87,"column":1}},"key":"X6JNs4NPDX"},{"type":"inlineCode","value":"https://github.com/ProjectPythia/mpasviewer-cookbook","position":{"start":{"line":87,"column":1},"end":{"line":87,"column":1}},"key":"ySEtdiTkOp"},{"type":"text","value":" repository:","position":{"start":{"line":87,"column":1},"end":{"line":87,"column":1}},"key":"QQvXXWF2j5"}],"key":"tZQ4rBl36k"},{"type":"code","lang":"bash","value":" git clone https://github.com/ProjectPythia/mpasviewer-cookbook.git","position":{"start":{"line":89,"column":1},"end":{"line":91,"column":1}},"key":"dXKgKMjenJ"}],"key":"qSBYTuCcvm"},{"type":"listItem","spread":true,"position":{"start":{"line":93,"column":1},"end":{"line":96,"column":1}},"children":[{"type":"paragraph","position":{"start":{"line":93,"column":1},"end":{"line":93,"column":1}},"children":[{"type":"text","value":"Move into the ","position":{"start":{"line":93,"column":1},"end":{"line":93,"column":1}},"key":"wfgqNCqsCI"},{"type":"inlineCode","value":"mpasviewer-cookbook","position":{"start":{"line":93,"column":1},"end":{"line":93,"column":1}},"key":"biaX36t0oR"},{"type":"text","value":" directory","position":{"start":{"line":93,"column":1},"end":{"line":93,"column":1}},"key":"wREjmCOoMb"}],"key":"mYTEgxt1Gb"},{"type":"code","lang":"bash","value":"cd mpasviewer-cookbook","position":{"start":{"line":94,"column":1},"end":{"line":96,"column":1}},"key":"e5YDQ05VDS"}],"key":"X85aqNfJJ1"},{"type":"listItem","spread":true,"position":{"start":{"line":97,"column":1},"end":{"line":101,"column":1}},"children":[{"type":"paragraph","position":{"start":{"line":97,"column":1},"end":{"line":97,"column":1}},"children":[{"type":"text","value":"Create and activate your conda environment from the ","position":{"start":{"line":97,"column":1},"end":{"line":97,"column":1}},"key":"d8Jt4uS9My"},{"type":"inlineCode","value":"environment.yml","position":{"start":{"line":97,"column":1},"end":{"line":97,"column":1}},"key":"GE6bUuHBkT"},{"type":"text","value":" file","position":{"start":{"line":97,"column":1},"end":{"line":97,"column":1}},"key":"QeXUZ9HiJz"}],"key":"bhTRpVdWjx"},{"type":"code","lang":"bash","value":"conda env create -f environment.yml\nconda activate mpasviewer-cookbook","position":{"start":{"line":98,"column":1},"end":{"line":101,"column":1}},"key":"VFOwQMVadu"}],"key":"LlmVdOxfnB"},{"type":"listItem","spread":true,"position":{"start":{"line":102,"column":1},"end":{"line":106,"column":1}},"children":[{"type":"paragraph","position":{"start":{"line":102,"column":1},"end":{"line":102,"column":1}},"children":[{"type":"text","value":"Move into the ","position":{"start":{"line":102,"column":1},"end":{"line":102,"column":1}},"key":"IvxNGfVtfj"},{"type":"inlineCode","value":"notebooks","position":{"start":{"line":102,"column":1},"end":{"line":102,"column":1}},"key":"bedZF6D094"},{"type":"text","value":" directory and start up Jupyterlab","position":{"start":{"line":102,"column":1},"end":{"line":102,"column":1}},"key":"UEjMKvd4bR"}],"key":"emyDCAp5wn"},{"type":"code","lang":"bash","value":"cd notebooks/\njupyter lab","position":{"start":{"line":103,"column":1},"end":{"line":106,"column":1}},"key":"WfCc6g9M2G"}],"key":"p3Lz2INUPb"}],"key":"TlgjGZVKoY"}],"key":"w3PcGuzT0K"}],"key":"bdqpstH2gS"},"references":{"cite":{"order":["https://doi.org/10.5281/zenodo.20753191"],"data":{"https://doi.org/10.5281/zenodo.20753191":{"label":"https://doi.org/10.5281/zenodo.20753191","enumerator":"1","doi":"10.5281/ZENODO.20753191","html":"Bravo, J., Condo, B., Melissa, Z., Ge, M., & MPAS Viewer Cookbook contributors. (2026). <i>MPAS Viewer Cookbook</i>. Zenodo. <a target=\"_blank\" rel=\"noreferrer\" href=\"https://doi.org/10.5281/ZENODO.20753191\">10.5281/ZENODO.20753191</a>","url":"https://doi.org/10.5281/ZENODO.20753191"}}}},"footer":{"navigation":{"next":{"title":"MPAS Viewer","url":"/notebooks/introduction","group":"Introduction"}}},"domain":"http://localhost:3000"}